package/101903189.py
package/__init__.py
Topsis_Ravnoor_101903189-0.0.1.dist-info/METADATA
Topsis_Ravnoor_101903189-0.0.1.dist-info/WHEEL
Topsis_Ravnoor_101903189-0.0.1.dist-info/top_level.txt
Topsis_Ravnoor_101903189-0.0.1.dist-info/RECORD
